{"index.md":"09b1edf9","diary-pit_index.md":"54185338","diary-pit_pc-css.md":"14913f23","study-blog_browser-extend.md":"7766b182","study-blog_git-command.md":"7646cf8a","study-blog_npm-command.md":"86a9a8ce","study-blog_utils-network.md":"ee52cdba","diary-pit_h5-js.md":"c7c84972","study-blog_zsh.md":"82ce75ec","trick-list_css-record.md":"43abd331","trick-list_css-trick.md":"5cd5ecbc","trick-list_index.md":"805b141c","study-blog_vscode-config.md":"ae4f96d7","trick-list_utils-function.md":"88118a47","web-doc_js-base-api.md":"3660941e","study-blog_index.md":"332e4d3e","web-doc_index.md":"f339fe2e","web-doc_js-conversions.md":"c2650cc0","web-doc_js-types.md":"9999537b","trick-list_utils-library.md":"9a1e9283","web-doc_es6.md":"ce05a95c","web-doc_http.md":"e83d9f89","web-doc_page-rendering.md":"e69b5032","web-doc_module.md":"85ae6b93","trick-list_utils-regexp.md":"03ee856c","web-doc_browser-base.md":"16d2cd38","web-doc_html.md":"cb1041e3","web-doc_tcp.md":"3ff6d479","trick-list_sass-record.md":"be0294b6"}
